alidilara/__init__.py
alidilara/our_codes.py
alidilara-0.0.1.dist-info/LICENSE.txt
alidilara-0.0.1.dist-info/METADATA
alidilara-0.0.1.dist-info/WHEEL
alidilara-0.0.1.dist-info/top_level.txt
alidilara-0.0.1.dist-info/RECORD
