Metadata-Version: 2.1
Name: alidilara
Version: 0.0.1
Summary: A simple package for calculating statistics.
Author-email: Ali DUMAN <alidumanyp@gmail.com>
Project-URL: Homepage, https://github.com/alidumanyp/alidilara
Keywords: alidumanyp,alidilara
Classifier: Development Status :: 3 - Alpha
Classifier: Intended Audience :: Developers
Classifier: License :: OSI Approved :: MIT License
Classifier: Programming Language :: Python :: 3
Classifier: Operating System :: OS Independent
Requires-Python: >=3.6.0
License-File: LICENSE.txt
